{
    "total_wire_length": 17679.663246066782,
    "total_jumper_length": 40.561889026200824,
    "total_jumper_count": 8,
    "center_node_count": 292,
    "edge_node_count": 72,
    "total_node_count": 364,
    "reachable_node_count": [
        364.0,
        364.0,
        364.0,
        [
            364.0,
            364.0,
            364.0,
            364.0,
            364.0,
            364.0
        ],
        364.0
    ],
    "unreachable_node_count": [
        0.0,
        0.0,
        0.0,
        [
            0.0,
            0.0,
            0.0,
            0.0,
            0.0,
            0.0
        ],
        0.0
    ],
    "reachable_wire_length": [
        17679.663246066782,
        17679.663246066782,
        17679.663246066782,
        [
            17679.663246066782,
            17679.663246066782,
            17679.663246066782,
            17679.663246066782,
            17679.663246066782,
            17679.663246066782
        ],
        17679.66324606678
    ],
    "unreachable_wire_length": [
        0.0,
        0.0,
        0.0,
        [
            0.0,
            0.0,
            0.0,
            0.0,
            0.0,
            0.0
        ],
        0.0
    ],
    "reachable_jumper_length": [
        40.561889026200824,
        40.561889026200824,
        40.561889026200824,
        [
            40.561889026200824,
            40.561889026200824,
            40.561889026200824,
            40.561889026200824,
            40.561889026200824,
            40.561889026200824
        ],
        40.56188902620083
    ],
    "unreachable_jumper_length": [
        0.0,
        0.0,
        0.0,
        [
            0.0,
            0.0,
            0.0,
            0.0,
            0.0,
            0.0
        ],
        0.0
    ],
    "reachable_jumper_count": [
        8.0,
        8.0,
        8.0,
        [
            8.0,
            8.0,
            8.0,
            8.0,
            8.0,
            8.0
        ],
        8.0
    ],
    "unreachable_jumper_count": [
        0.0,
        0.0,
        0.0,
        [
            0.0,
            0.0,
            0.0,
            0.0,
            0.0,
            0.0
        ],
        0.0
    ],
    "shortest_path": {
        "percent_useful_node_count": [
            0.75,
            0.7472527472527473,
            0.7527472527472527,
            [
                0.714010989010989,
                0.7195054945054945,
                0.7362637362637363,
                0.7589285714285714,
                0.7695054945054945,
                0.7774725274725275
            ],
            0.7474725274725276
        ],
        "percent_useful_wire_length": 58.7368937504853,
        "percent_reachable_sensors": 0.3875,
        "percent_useful_jumper_count": [
            0.875,
            0.875,
            0.875,
            [
                0.625,
                0.625,
                0.75,
                0.875,
                1.0,
                1.0
            ],
            0.84375
        ],
        "percent_useful_jumper_length": [
            0.25,
            0.125,
            0.25,
            [
                0.125,
                0.125,
                0.125,
                0.25,
                0.25,
                0.25
            ],
            0.19375
        ],
        "percent_unreachable_bc_short_jumper": 0.6125,
        "percent_multiroute_reached_nodes": [
            0.3613564789922421,
            0.35712669043173206,
            0.3652774507495487,
            [
                0.33703500203500203,
                0.3404700786138296,
                0.3522498567182481,
                0.3741919191919192,
                0.3872416280553783,
                0.38897184551886793
            ],
            0.3631518626291615
        ],
        "path_length_max": [
            1490.9553811604828,
            1481.765025758978,
            1490.9553811604828
        ],
        "path_length_avg": [
            632.0709015408603,
            627.4287225219399,
            636.934633965976,
            [
                167.0393876277755,
                242.598950453844,
                393.22147424320025,
                874.4037325630686,
                1055.1018948479875,
                1146.6857871154239
            ],
            641.2227337032351
        ],
        "path_node_count_max": [
            41.0,
            39.0,
            41.0
        ],
        "path_node_count_avg": [
            16.0,
            16.0,
            16.0,
            [
                4.0,
                6.0,
                10.0,
                24.0,
                28.0,
                31.0
            ],
            16.784412903225807
        ],
        "path_jumper_count_max": [
            3.0,
            2.0,
            3.0
        ],
        "path_jumper_count_avg": [
            1.0,
            1.0,
            1.0,
            [
                0.0,
                0.0,
                0.0,
                1.0,
                1.0,
                2.0
            ],
            0.6524645161290322
        ],
        "path_sensor_jumper_length_max": [
            9.999986743831577,
            9.999097862189487,
            9.999986743831577
        ],
        "path_sensor_jumper_length_avg": [
            4.571193628587237,
            4.524562864789502,
            4.623873524953073,
            [
                0.4409521806933931,
                0.8790459710050031,
                2.191712469845575,
                7.107944970425382,
                8.79491854874413,
                9.389903807325654
            ],
            4.704419282116423
        ],
        "path_router_node_branches_max": [
            2.0,
            2.0,
            2.0
        ],
        "path_router_node_branches_avg": [
            2.0,
            2.0,
            2.0,
            [
                2.0,
                2.0,
                2.0,
                2.0,
                2.0,
                2.0
            ],
            2.0
        ],
        "graph_max_wire_length": [
            1233.9732491726945,
            1206.184302276415,
            1264.9008017077426,
            [
                976.827840824053,
                1010.9606437099299,
                1098.0891454498344,
                1348.3468723644162,
                1413.7605311677137,
                1451.2433072665253
            ],
            1221.0788623018682
        ],
        "graph_avg_wire_length": [
            630.0025959343288,
            606.1135334667497,
            649.0671623606395,
            [
                532.4119458124379,
                545.001727545958,
                580.5012684946839,
                708.7335502836017,
                742.5299792549931,
                779.9405571150045
            ],
            641.877678984122
        ],
        "graph_max_node_count": [
            35.0,
            34.0,
            35.0,
            [
                28.95,
                29.9,
                32.0,
                38.0,
                39.0,
                40.0
            ],
            34.57
        ],
        "graph_avg_node_count": [
            16.838079975579973,
            16.53185595567867,
            17.53993818681319,
            [
                14.90285434262707,
                15.302770083102493,
                15.977295431840886,
                19.038404620241636,
                20.212126434068267,
                20.79436396936397
            ],
            17.469239517367765
        ],
        "graph_max_jumper_count": [
            2.0,
            2.0,
            2.0,
            [
                2.0,
                2.0,
                2.0,
                2.0,
                2.0,
                2.049999999999997
            ],
            2.05
        ],
        "graph_avg_jumper_count": [
            0.6153846153846154,
            0.5989010989010989,
            0.6401098901098901,
            [
                0.5178351951079224,
                0.5264623955431755,
                0.5638888888888889,
                0.6847527472527473,
                0.8923712650985379,
                0.9175824175824175
            ],
            0.6602448503598899
        ]
    },
    "least_jumper_path": {
        "percent_useful_node_count": [
            0.7252747252747253,
            0.7211538461538461,
            0.728021978021978,
            [
                0.6978021978021978,
                0.7030219780219781,
                0.7115384615384616,
                0.7362637362637363,
                0.7417582417582418,
                0.7445054945054945
            ],
            0.7232967032967033
        ],
        "percent_useful_wire_length": 58.80111535249701,
        "percent_reachable_sensors": 0.3875,
        "percent_useful_jumper_count": [
            0.7910933683409216,
            0.7910933683409216,
            0.7910933683409216,
            [
                0.563091491350476,
                0.5744849025042099,
                0.6786833874254855,
                0.9352959368562205,
                1.0,
                1.0
            ],
            0.7956723757190244
        ],
        "percent_useful_jumper_length": [
            0.12440900859790578,
            0.11015656963526377,
            0.12440900859790578,
            [
                0.014252438962641995,
                0.014252438962641995,
                0.014252438962641995,
                0.12440900859790578,
                0.3789345158248079,
                0.3789345158248079
            ],
            0.1364898064844883
        ],
        "percent_unreachable_bc_short_jumper": 0.6125,
        "percent_multiroute_reached_nodes": [
            0.36194388358977925,
            0.35661764705882354,
            0.3676086198884758,
            [
                0.3316801778056391,
                0.3394373191078826,
                0.34850049384933107,
                0.37065637065637064,
                0.38170042675963217,
                0.3865654363677366
            ],
            0.3602893415946989
        ],
        "path_length_max": [
            1646.9783732363603,
            1618.017919805484,
            1646.9783732363603
        ],
        "path_length_avg": [
            652.3926080689612,
            647.4915631405156,
            657.4149608174547,
            [
                169.18582843230578,
                248.6840623810495,
                416.94543309478496,
                931.1755582200292,
                1151.9349045600954,
                1258.4046786580188
            ],
            679.788979338343
        ],
        "path_node_count_max": [
            42.0,
            42.0,
            42.0
        ],
        "path_node_count_avg": [
            17.0,
            16.0,
            17.0,
            [
                4.0,
                6.0,
                10.0,
                25.0,
                30.0,
                33.0
            ],
            17.465754838709678
        ],
        "path_jumper_count_max": [
            1.0,
            1.0,
            1.0
        ],
        "path_jumper_count_avg": [
            1.0,
            0.0,
            1.0,
            [
                0.0,
                0.0,
                0.0,
                1.0,
                1.0,
                1.0
            ],
            0.5044645161290322
        ],
        "path_sensor_jumper_length_max": [
            9.999986743831577,
            9.999097862189487,
            9.999986743831577
        ],
        "path_sensor_jumper_length_avg": [
            4.571193628587237,
            4.5252802318090986,
            4.622799280224745,
            [
                0.4409521806933931,
                0.8790459710050031,
                2.191712469845575,
                7.107944970425382,
                8.79491854874413,
                9.389903807325654
            ],
            4.704419282116423
        ],
        "path_router_node_branches_max": [
            2.0,
            2.0,
            2.0
        ],
        "path_router_node_branches_avg": [
            2.0,
            2.0,
            2.0,
            [
                2.0,
                2.0,
                2.0,
                2.0,
                2.0,
                2.0
            ],
            2.0
        ],
        "graph_max_wire_length": [
            1319.679299652847,
            1282.5221699658573,
            1366.0129333629006,
            [
                1021.1392252402377,
                1106.772822035604,
                1219.173991284714,
                1440.5860886969044,
                1537.5364939436881,
                1567.2952040812572
            ],
            1320.1232135963126
        ],
        "graph_avg_wire_length": [
            629.6533424800741,
            610.3419913168067,
            643.1630554683186,
            [
                542.0061634069857,
                545.4026199418706,
                586.4968970838239,
                729.3925304555363,
                765.5043698102022,
                785.5271147077015
            ],
            649.5015018189903
        ],
        "graph_max_node_count": [
            36.0,
            35.0,
            37.0,
            [
                28.95,
                30.0,
                32.0,
                38.25,
                41.0,
                42.0
            ],
            35.6
        ],
        "graph_avg_node_count": [
            16.735734190113753,
            16.379787693803685,
            17.141463320013965,
            [
                14.642894456289978,
                15.01859295125639,
                15.75702607615894,
                19.236013374285605,
                20.1644995210728,
                20.654209795979597
            ],
            17.31872011335378
        ],
        "graph_max_jumper_count": [
            1.0,
            1.0,
            1.0,
            [
                1.0,
                1.0,
                1.0,
                1.0,
                1.0,
                1.0
            ],
            1.0
        ],
        "graph_avg_jumper_count": [
            0.47214076246334313,
            0.4576458273860501,
            0.4757763975155279,
            [
                0.3985004540722529,
                0.40956907139424364,
                0.4452232606438214,
                0.48845591655039533,
                0.49833469833469834,
                0.5034752757849263
            ],
            0.4606986172966391
        ]
    }
}