{
    "total_wire_length": 44094.27292415013,
    "total_jumper_length": 10646.73541238738,
    "total_jumper_count": 287,
    "center_node_count": 1471,
    "edge_node_count": 211,
    "total_node_count": 1682,
    "reachable_node_count": [
        1682.0,
        1682.0,
        1682.0,
        [
            1682.0,
            1682.0,
            1682.0,
            1682.0,
            1682.0,
            1682.0
        ],
        1682.0
    ],
    "unreachable_node_count": [
        0.0,
        0.0,
        0.0,
        [
            0.0,
            0.0,
            0.0,
            0.0,
            0.0,
            0.0
        ],
        0.0
    ],
    "reachable_wire_length": [
        44094.27292415014,
        44094.27292415014,
        44094.27292415014,
        [
            44094.27292415014,
            44094.27292415014,
            44094.27292415014,
            44094.27292415014,
            44094.27292415014,
            44094.27292415014
        ],
        44094.27292415014
    ],
    "unreachable_wire_length": [
        0.0,
        0.0,
        0.0,
        [
            0.0,
            0.0,
            0.0,
            0.0,
            0.0,
            0.0
        ],
        0.0
    ],
    "reachable_jumper_length": [
        10646.735412387376,
        10646.735412387376,
        10646.735412387376,
        [
            10646.735412387376,
            10646.735412387376,
            10646.735412387376,
            10646.735412387376,
            10646.735412387376,
            10646.735412387376
        ],
        10646.735412387377
    ],
    "unreachable_jumper_length": [
        0.0,
        0.0,
        0.0,
        [
            0.0,
            0.0,
            0.0,
            0.0,
            0.0,
            0.0
        ],
        0.0
    ],
    "reachable_jumper_count": [
        287.0,
        287.0,
        287.0,
        [
            287.0,
            287.0,
            287.0,
            287.0,
            287.0,
            287.0
        ],
        287.0
    ],
    "unreachable_jumper_count": [
        0.0,
        0.0,
        0.0,
        [
            0.0,
            0.0,
            0.0,
            0.0,
            0.0,
            0.0
        ],
        0.0
    ],
    "shortest_path": {
        "percent_useful_node_count": [
            0.7615933412604042,
            0.7586206896551724,
            0.7633769322235434,
            [
                0.7461355529131986,
                0.7490487514863258,
                0.7538644470868014,
                0.7670927467300832,
                0.7730083234244947,
                0.7771403091557669
            ],
            0.761141498216409
        ],
        "percent_useful_wire_length": 58.58767838506876,
        "percent_reachable_sensors": 1.0,
        "percent_useful_jumper_count": [
            0.27177700348432055,
            0.2682926829268293,
            0.27526132404181186,
            [
                0.23658536585365852,
                0.24738675958188153,
                0.2578397212543554,
                0.28310104529616725,
                0.2930313588850174,
                0.3033101045296167
            ],
            0.2697560975609756
        ],
        "percent_useful_jumper_length": [
            0.013937282229965157,
            0.013937282229965157,
            0.017421602787456445,
            [
                0.010452961672473868,
                0.010452961672473868,
                0.013937282229965157,
                0.017421602787456445,
                0.017770034843205603,
                0.020905923344947737
            ],
            0.01515679442508711
        ],
        "percent_unreachable_bc_short_jumper": 0.0,
        "percent_multiroute_reached_nodes": [
            0.32199457307816437,
            0.3197852760736196,
            0.32398733486188447,
            [
                0.3071500762286517,
                0.309280526754612,
                0.3148009831654112,
                0.3347084162001289,
                0.34140297530111574,
                0.3448618224644628
            ],
            0.32421778225653414
        ],
        "path_length_max": [
            1952.1800634296276,
            1932.5500212463564,
            1952.1800634296276
        ],
        "path_length_avg": [
            633.5389656716602,
            631.3469479753103,
            635.675545396973,
            [
                197.30332329209452,
                272.52591874414725,
                437.7766692479978,
                845.7422689573528,
                1085.7664207695195,
                1230.9437055950107
            ],
            660.7486536042662
        ],
        "path_node_count_max": [
            94.0,
            94.0,
            94.0
        ],
        "path_node_count_avg": [
            30.0,
            30.0,
            30.0,
            [
                9.0,
                13.0,
                21.0,
                40.0,
                52.0,
                59.0
            ],
            31.42579
        ],
        "path_jumper_count_max": [
            23.0,
            21.0,
            23.0
        ],
        "path_jumper_count_avg": [
            1.0,
            1.0,
            1.0,
            [
                0.0,
                0.0,
                1.0,
                3.0,
                7.0,
                9.0
            ],
            2.36448
        ],
        "path_sensor_jumper_length_max": [
            50.31932936916346,
            47.12622420812607,
            50.31932936916346
        ],
        "path_sensor_jumper_length_avg": [
            10.006059237315686,
            9.923874406552022,
            10.09215486423855,
            [
                0.6823910415100163,
                1.4140145362398926,
                3.9756998400571,
                18.14119841333354,
                25.3733565566899,
                29.087762998505905
            ],
            11.823374988181758
        ],
        "path_router_node_branches_max": [
            5.0,
            5.0,
            5.0
        ],
        "path_router_node_branches_avg": [
            2.0,
            2.0,
            2.0,
            [
                2.0,
                2.0,
                2.0,
                2.0,
                2.0,
                3.0
            ],
            2.1345707656612527
        ],
        "graph_max_wire_length": [
            1365.2941267946521,
            1285.4032085501262,
            1417.3433794278376,
            [
                1088.4587932795523,
                1130.7492300054203,
                1211.909992156726,
                1494.5343862526718,
                1694.0045808285886,
                1830.0667141154918
            ],
            1382.6056905837968
        ],
        "graph_avg_wire_length": [
            616.0744437064673,
            594.5489122638578,
            644.5186296788471,
            [
                521.0012900471412,
                533.2204657758211,
                566.8088499453629,
                687.2573239759065,
                822.774159307899,
                949.133357010254
            ],
            650.9530223852412
        ],
        "graph_max_node_count": [
            66.0,
            63.5,
            69.0,
            [
                51.0,
                53.0,
                59.0,
                74.0,
                81.20000000000002,
                92.05
            ],
            67.09
        ],
        "graph_avg_node_count": [
            30.385850178359096,
            29.2778983353151,
            31.3330112960761,
            [
                26.376354244450138,
                26.909334126040427,
                28.138689180880025,
                33.95273483947682,
                39.55582639714626,
                43.98439357907253
            ],
            31.860613051871404
        ],
        "graph_max_jumper_count": [
            14.0,
            14.0,
            14.0,
            [
                10.95,
                12.0,
                13.0,
                15.25,
                18.10000000000001,
                20.0
            ],
            14.56
        ],
        "graph_avg_jumper_count": [
            2.0624256837098693,
            1.9024970273483948,
            2.245251189060642,
            [
                1.3810931193758333,
                1.4146852726132653,
                1.5942891136228436,
                2.7996588464022434,
                3.6070154577883478,
                6.29387633769322
            ],
            2.51611055413489
        ]
    },
    "least_jumper_path": {
        "percent_useful_node_count": [
            0.7294887039239001,
            0.727705112960761,
            0.7312722948870393,
            [
                0.7145957193816885,
                0.7169441141498216,
                0.72294887039239,
                0.7342449464922711,
                0.7402497027348395,
                0.7455410225921522
            ],
            0.7291141498216409
        ],
        "percent_useful_wire_length": 55.58222167801094,
        "percent_reachable_sensors": 1.0,
        "percent_useful_jumper_count": [
            0.24290034009409475,
            0.2354476678739198,
            0.24976343939201728,
            [
                0.19362657996683566,
                0.20389971150547195,
                0.2219361191872202,
                0.25811827786774766,
                0.2698309153999905,
                0.28170188919061245
            ],
            0.23961243928329534
        ],
        "percent_useful_jumper_length": [
            0.017527412644866444,
            0.01613271704152207,
            0.01821030787027668,
            [
                0.007080900063814377,
                0.008543199224387453,
                0.012338362358725829,
                0.0203816031391872,
                0.0228355138813889,
                0.024034517471191494
            ],
            0.016494415854201073
        ],
        "percent_unreachable_bc_short_jumper": 0.0,
        "percent_multiroute_reached_nodes": [
            0.28769865923803034,
            0.28605878825802455,
            0.28876045997059596,
            [
                0.277283202715454,
                0.2800657648925038,
                0.2831698476343224,
                0.29114300139816685,
                0.29545006702954146,
                0.298479176209137
            ],
            0.28754268532168814
        ],
        "path_length_max": [
            2113.0379411432295,
            2073.99882036133,
            2113.0379411432295
        ],
        "path_length_avg": [
            707.1051971506452,
            704.4156573703395,
            709.6035510879938,
            [
                206.83350543349408,
                292.7513333878351,
                479.59170672601635,
                942.3360617263886,
                1180.513747047931,
                1329.711862008973
            ],
            727.1404582133989
        ],
        "path_node_count_max": [
            105.0,
            103.0,
            105.0
        ],
        "path_node_count_avg": [
            34.0,
            34.0,
            34.0,
            [
                9.0,
                14.0,
                23.0,
                46.0,
                58.0,
                66.0
            ],
            35.31193
        ],
        "path_jumper_count_max": [
            3.0,
            3.0,
            3.0
        ],
        "path_jumper_count_avg": [
            1.0,
            1.0,
            1.0,
            [
                0.0,
                0.0,
                0.0,
                1.0,
                2.0,
                2.0
            ],
            0.87126
        ],
        "path_sensor_jumper_length_max": [
            50.31932936916346,
            47.12622420812607,
            50.31932936916346
        ],
        "path_sensor_jumper_length_avg": [
            10.006059237315686,
            9.918979257879169,
            10.083182286825336,
            [
                0.6823910415100163,
                1.4140145362398926,
                3.9756998400571,
                18.14119841333354,
                25.3733565566899,
                29.087762998505905
            ],
            11.823374988181758
        ],
        "path_router_node_branches_max": [
            2.0,
            2.0,
            2.0
        ],
        "path_router_node_branches_avg": [
            2.0,
            2.0,
            2.0,
            [
                2.0,
                2.0,
                2.0,
                2.0,
                2.0,
                2.0
            ],
            2.0
        ],
        "graph_max_wire_length": [
            1488.3472102430985,
            1421.1445314039493,
            1534.4445317799773,
            [
                1200.265109335628,
                1240.549221834839,
                1336.1290741624657,
                1613.796849656223,
                1839.8097523442439,
                1981.082753392614
            ],
            1508.0559766785293
        ],
        "graph_avg_wire_length": [
            579.7101923904447,
            565.3456627257381,
            603.3967052200028,
            [
                499.6071062747113,
                511.80991736563914,
                540.2657089698602,
                648.4993133819503,
                729.7673895664517,
                893.1208088400285
            ],
            612.7558017288382
        ],
        "graph_max_node_count": [
            75.0,
            71.0,
            78.0,
            [
                61.0,
                63.0,
                67.0,
                82.25,
                94.20000000000002,
                101.05
            ],
            76.48
        ],
        "graph_avg_node_count": [
            29.364163480223155,
            28.520138358849675,
            30.758088285938896,
            [
                24.798039796252432,
                25.635186663506754,
                26.746874462966147,
                32.24326436529947,
                36.74638466130805,
                45.08526894684518
            ],
            30.758876071062264
        ],
        "graph_max_jumper_count": [
            2.0,
            2.0,
            2.0,
            [
                1.0,
                1.0,
                1.0,
                2.0,
                2.0,
                2.0
            ],
            1.66
        ],
        "graph_avg_jumper_count": [
            0.5630212536992198,
            0.5249114868680086,
            0.6614430771257112,
            [
                0.4375205852029129,
                0.44950122778561713,
                0.4964512123658448,
                0.8041143247269116,
                1.0006648936170213,
                1.0858144240304537
            ],
            0.6618571563472674
        ]
    }
}