{
    "total_wire_length": 117083.00003792919,
    "total_jumper_length": 6368.905176358807,
    "total_jumper_count": 297,
    "center_node_count": 492,
    "edge_node_count": 368,
    "total_node_count": 860,
    "reachable_node_count": [
        860.0,
        860.0,
        860.0,
        [
            860.0,
            860.0,
            860.0,
            860.0,
            860.0,
            860.0
        ],
        860.0
    ],
    "unreachable_node_count": [
        0.0,
        0.0,
        0.0,
        [
            0.0,
            0.0,
            0.0,
            0.0,
            0.0,
            0.0
        ],
        0.0
    ],
    "reachable_wire_length": [
        117083.00003792929,
        117083.00003792929,
        117083.00003792929,
        [
            117083.00003792929,
            117083.00003792929,
            117083.00003792929,
            117083.00003792929,
            117083.00003792929,
            117083.00003792929
        ],
        117083.00003792929
    ],
    "unreachable_wire_length": [
        0.0,
        0.0,
        0.0,
        [
            0.0,
            0.0,
            0.0,
            0.0,
            0.0,
            0.0
        ],
        0.0
    ],
    "reachable_jumper_length": [
        6368.905176358806,
        6368.905176358806,
        6368.905176358806,
        [
            6368.905176358806,
            6368.905176358806,
            6368.905176358806,
            6368.905176358806,
            6368.905176358806,
            6368.905176358806
        ],
        6368.905176358804
    ],
    "unreachable_jumper_length": [
        0.0,
        0.0,
        0.0,
        [
            0.0,
            0.0,
            0.0,
            0.0,
            0.0,
            0.0
        ],
        0.0
    ],
    "reachable_jumper_count": [
        297.0,
        297.0,
        297.0,
        [
            297.0,
            297.0,
            297.0,
            297.0,
            297.0,
            297.0
        ],
        297.0
    ],
    "unreachable_jumper_count": [
        0.0,
        0.0,
        0.0,
        [
            0.0,
            0.0,
            0.0,
            0.0,
            0.0,
            0.0
        ],
        0.0
    ],
    "shortest_path": {
        "percent_useful_node_count": [
            0.6936046511627907,
            0.6895348837209302,
            0.6976744186046512,
            [
                0.6673255813953489,
                0.6708139534883721,
                0.6813953488372093,
                0.7026162790697674,
                0.708139534883721,
                0.7105813953488371
            ],
            0.6914767441860465
        ],
        "percent_useful_wire_length": 32.77589017422095,
        "percent_reachable_sensors": 1.0,
        "percent_useful_jumper_count": [
            0.297979797979798,
            0.28619528619528617,
            0.30303030303030304,
            [
                0.23232323232323232,
                0.24545454545454545,
                0.265993265993266,
                0.31313131313131315,
                0.32693602693602697,
                0.3367003367003367
            ],
            0.2914814814814815
        ],
        "percent_useful_jumper_length": [
            0.013468013468013467,
            0.013468013468013467,
            0.013468013468013467,
            [
                0.010101010101010102,
                0.010101010101010102,
                0.010101010101010102,
                0.016835016835016835,
                0.016835016835016835,
                0.020202020202020204
            ],
            0.014107744107744107
        ],
        "percent_unreachable_bc_short_jumper": 0.0,
        "percent_multiroute_reached_nodes": [
            0.41347729789590254,
            0.4059898113905131,
            0.4217320290135057,
            [
                0.35656039409211,
                0.36717549829849294,
                0.3934484460212529,
                0.4380858777792338,
                0.46386870472200403,
                0.47098963811304584
            ],
            0.41486303758361925
        ],
        "path_length_max": [
            2707.4549522458674,
            2653.1776408726237,
            2707.4549522458674
        ],
        "path_length_avg": [
            887.5063772565209,
            884.6438704342607,
            890.5892314758202,
            [
                270.9066928999752,
                381.6281342585379,
                611.0078613254525,
                1184.1074277261578,
                1486.6232796000816,
                1679.531291633849
            ],
            918.4087667714706
        ],
        "path_node_count_max": [
            48.0,
            48.0,
            48.0
        ],
        "path_node_count_avg": [
            13.0,
            13.0,
            13.0,
            [
                4.0,
                5.0,
                9.0,
                18.0,
                24.0,
                28.0
            ],
            14.15725
        ],
        "path_jumper_count_max": [
            21.0,
            19.0,
            21.0
        ],
        "path_jumper_count_avg": [
            1.0,
            1.0,
            1.0,
            [
                0.0,
                0.0,
                1.0,
                3.0,
                5.0,
                7.0
            ],
            1.97472
        ],
        "path_sensor_jumper_length_max": [
            37.112296580090394,
            33.43024179765409,
            37.112296580090394
        ],
        "path_sensor_jumper_length_avg": [
            6.77273961452689,
            6.726020668072232,
            6.825217839893769,
            [
                0.5960499734241392,
                1.1773704920167671,
                3.0903261678878344,
                11.605935883705838,
                15.89155145922033,
                18.07548999210126
            ],
            7.740867074860772
        ],
        "path_router_node_branches_max": [
            5.0,
            4.0,
            5.0
        ],
        "path_router_node_branches_avg": [
            2.0,
            2.0,
            2.0,
            [
                2.0,
                2.0,
                2.0,
                3.0,
                3.0,
                4.0
            ],
            2.358490566037736
        ],
        "graph_max_wire_length": [
            1896.4717211529542,
            1821.5504543583631,
            1955.7609294842307,
            [
                1500.082949970436,
                1554.3668643350727,
                1666.302330180999,
                2093.490713236194,
                2395.911239210879,
                2521.277918128356
            ],
            1920.648089289825
        ],
        "graph_avg_wire_length": [
            865.0245833921097,
            836.667541486787,
            901.8692206439804,
            [
                723.2185965800869,
                735.7405345941796,
                775.2154782741634,
                981.6124258206698,
                1106.5212860908011,
                1265.576989965064
            ],
            902.588480311914
        ],
        "graph_max_node_count": [
            35.0,
            34.0,
            36.0,
            [
                29.0,
                30.0,
                32.0,
                39.0,
                42.10000000000001,
                44.05
            ],
            35.82
        ],
        "graph_avg_node_count": [
            14.15420893189616,
            13.499344692005243,
            14.470304540005994,
            [
                11.632918475416396,
                11.747113195999988,
                12.422127517068533,
                15.65157368013559,
                18.479824190321864,
                19.679520744177125
            ],
            14.563569282326046
        ],
        "graph_max_jumper_count": [
            14.0,
            13.5,
            14.0,
            [
                9.0,
                9.9,
                13.0,
                15.0,
                16.0,
                19.0
            ],
            13.7
        ],
        "graph_avg_jumper_count": [
            1.8120296327678629,
            1.7063768894395401,
            1.916278029110936,
            [
                1.4188198198198199,
                1.4432652743142145,
                1.6196185980036644,
                2.15639521768554,
                2.758716356107661,
                3.133126200900181
            ],
            2.0263162115168836
        ]
    },
    "least_jumper_path": {
        "percent_useful_node_count": [
            0.5453488372093023,
            0.5430232558139535,
            0.5465116279069767,
            [
                0.5348255813953487,
                0.5382558139534884,
                0.541860465116279,
                0.55,
                0.5534883720930233,
                0.5547093023255815
            ],
            0.5454651162790697
        ],
        "percent_useful_wire_length": 31.52171430241895,
        "percent_reachable_sensors": 1.0,
        "percent_useful_jumper_count": [
            0.2651586545591379,
            0.2588382546547874,
            0.27158179419773404,
            [
                0.20787456369808893,
                0.2164214743892117,
                0.2411107109064612,
                0.2851419404167881,
                0.30427967518972504,
                0.310269790556819
            ],
            0.26341324907284397
        ],
        "percent_useful_jumper_length": [
            0.01243719737481373,
            0.011236534263227675,
            0.013649218026126944,
            [
                0.0077347790305720854,
                0.0077347790305720854,
                0.009425904520560626,
                0.016307764639781668,
                0.02000209058189347,
                0.0225399132170059
            ],
            0.013181491026522631
        ],
        "percent_unreachable_bc_short_jumper": 0.0,
        "percent_multiroute_reached_nodes": [
            0.4335803026880506,
            0.4288734521292661,
            0.437566067653277,
            [
                0.3995039797244486,
                0.40494524647010627,
                0.4195711401911376,
                0.4451476793248945,
                0.4595169755617517,
                0.4641384630609234
            ],
            0.43311736108248927
        ],
        "path_length_max": [
            2925.0739716511493,
            2914.4219424710773,
            2925.0739716511493
        ],
        "path_length_avg": [
            992.6369949821624,
            989.0520862394125,
            996.2274397750955,
            [
                285.2128220466837,
                406.2027078810549,
                658.9877582594315,
                1317.3043204246671,
                1622.258067978814,
                1809.2539978185378
            ],
            1009.3509090270413
        ],
        "path_node_count_max": [
            39.0,
            39.0,
            39.0
        ],
        "path_node_count_avg": [
            14.0,
            14.0,
            14.0,
            [
                4.0,
                5.0,
                9.0,
                18.0,
                22.0,
                24.0
            ],
            13.7745
        ],
        "path_jumper_count_max": [
            3.0,
            3.0,
            3.0
        ],
        "path_jumper_count_avg": [
            1.0,
            1.0,
            1.0,
            [
                0.0,
                0.0,
                0.0,
                1.0,
                1.0,
                2.0
            ],
            0.81419
        ],
        "path_sensor_jumper_length_max": [
            37.112296580090394,
            33.43024179765409,
            37.112296580090394
        ],
        "path_sensor_jumper_length_avg": [
            6.77273961452689,
            6.729341991122483,
            6.8227771688804,
            [
                0.5960499734241392,
                1.1773704920167671,
                3.0903261678878344,
                11.605935883705838,
                15.89155145922033,
                18.07548999210126
            ],
            7.740867074860772
        ],
        "path_router_node_branches_max": [
            5.0,
            4.0,
            5.0
        ],
        "path_router_node_branches_avg": [
            2.0,
            2.0,
            3.0,
            [
                2.0,
                2.0,
                2.0,
                3.0,
                4.0,
                4.0
            ],
            2.603960396039604
        ],
        "graph_max_wire_length": [
            2022.4161432256049,
            1951.0637323897845,
            2088.0629527165047,
            [
                1654.3173082863646,
                1679.1851404347647,
                1804.9021713057368,
                2257.5511997861327,
                2506.92621140712,
                2692.840694755574
            ],
            2052.2527228847043
        ],
        "graph_avg_wire_length": [
            996.659302240426,
            935.9353212476744,
            1042.6533183486952,
            [
                832.8798338191858,
                843.0501114252322,
                873.0490979566673,
                1119.6334025016358,
                1238.8281687377132,
                1346.9670735158354
            ],
            1019.4424133746617
        ],
        "graph_max_node_count": [
            27.5,
            26.0,
            28.0,
            [
                23.0,
                23.0,
                25.0,
                31.0,
                35.0,
                37.0
            ],
            28.29
        ],
        "graph_avg_node_count": [
            14.236390291631917,
            13.83064012490242,
            14.804651343439794,
            [
                12.12133457165372,
                12.173993966419076,
                12.59404600811908,
                15.8442543219702,
                17.641913989791142,
                18.874282635259522
            ],
            14.633598688979093
        ],
        "graph_max_jumper_count": [
            2.0,
            2.0,
            2.0,
            [
                1.0,
                1.0,
                1.0,
                2.0,
                2.0,
                2.0
            ],
            1.67
        ],
        "graph_avg_jumper_count": [
            0.6637018274993741,
            0.6507060349641945,
            0.7085970114876343,
            [
                0.6172819419886469,
                0.6228996890852561,
                0.6402116402116402,
                0.9344168312486285,
                0.9867471655173361,
                1.0848800303253832
            ],
            0.7688585236668329
        ]
    }
}