{
    "total_wire_length": 5612.037013204241,
    "total_jumper_length": 0.0,
    "total_jumper_count": 0,
    "center_node_count": 25,
    "edge_node_count": 29,
    "total_node_count": 54,
    "reachable_node_count": [
        20.0,
        20.0,
        20.0,
        [
            6.0,
            6.0,
            8.0,
            20.0,
            20.0,
            20.0
        ],
        16.52
    ],
    "unreachable_node_count": [
        34.0,
        34.0,
        34.0,
        [
            34.0,
            34.0,
            34.0,
            46.0,
            48.0,
            48.0
        ],
        37.48
    ],
    "reachable_wire_length": [
        2155.3943022634608,
        2155.3943022634608,
        2155.3943022634608,
        [
            520.3268184806927,
            520.3268184806927,
            652.5887796490979,
            2283.7271128109896,
            2283.7271128109896,
            2283.7271128109896
        ],
        1768.4152346652068
    ],
    "unreachable_wire_length": [
        3456.6427109407805,
        3456.6427109407805,
        3456.6427109407805,
        [
            3328.309900393251,
            3328.309900393251,
            3328.309900393251,
            4959.448233555143,
            5091.710194723549,
            5091.710194723549
        ],
        3843.621778539035
    ],
    "reachable_jumper_length": [
        0.0,
        0.0,
        0.0,
        [
            0.0,
            0.0,
            0.0,
            0.0,
            0.0,
            0.0
        ],
        0.0
    ],
    "unreachable_jumper_length": [
        0.0,
        0.0,
        0.0,
        [
            0.0,
            0.0,
            0.0,
            0.0,
            0.0,
            0.0
        ],
        0.0
    ],
    "reachable_jumper_count": [
        0.0,
        0.0,
        0.0,
        [
            0.0,
            0.0,
            0.0,
            0.0,
            0.0,
            0.0
        ],
        0.0
    ],
    "unreachable_jumper_count": [
        0.0,
        0.0,
        0.0,
        [
            0.0,
            0.0,
            0.0,
            0.0,
            0.0,
            0.0
        ],
        0.0
    ],
    "shortest_path": {
        "percent_useful_node_count": [
            0.18518518518518517,
            0.16666666666666666,
            0.18518518518518517,
            [
                0.05555555555555555,
                0.05555555555555555,
                0.07407407407407407,
                0.18518518518518517,
                0.2037037037037037,
                0.2037037037037037
            ],
            0.15037037037037035
        ],
        "percent_useful_wire_length": 21.452537797702906,
        "percent_reachable_sensors": 0.08022,
        "percent_useful_jumper_count": [
            -1.0,
            -1.0,
            -1.0,
            [
                -1.0,
                -1.0,
                -1.0,
                -1.0,
                -1.0,
                -1.0
            ],
            -1.0
        ],
        "percent_useful_jumper_length": [
            -1.0,
            -1.0,
            -1.0,
            [
                -1.0,
                -1.0,
                -1.0,
                -1.0,
                -1.0,
                -1.0
            ],
            -1.0
        ],
        "percent_unreachable_bc_short_jumper": 0.74395,
        "percent_multiroute_reached_nodes": [
            0.7777777777777778,
            0.75,
            0.788888888888889,
            [
                0.6666666666666666,
                0.6666666666666666,
                0.7,
                0.8,
                0.9100000000000009,
                1.0
            ],
            0.7743080808080808
        ],
        "path_length_max": [
            1071.1055327213257,
            1052.7756285009516,
            1071.1055327213257
        ],
        "path_length_avg": [
            422.63728478415555,
            415.81787166273705,
            427.610955940994,
            [
                133.3416016279965,
                165.36942803157433,
                256.6149536417428,
                576.3919113508063,
                709.1402331733476,
                772.9927351767234
            ],
            428.812133904685
        ],
        "path_node_count_max": [
            7.0,
            7.0,
            7.0
        ],
        "path_node_count_avg": [
            2.0,
            2.0,
            2.0,
            [
                1.0,
                1.0,
                1.0,
                3.0,
                4.0,
                4.0
            ],
            2.419346796310147
        ],
        "path_jumper_count_max": [
            0.0,
            0.0,
            0.0
        ],
        "path_jumper_count_avg": [
            0.0,
            0.0,
            0.0,
            [
                0.0,
                0.0,
                0.0,
                0.0,
                0.0,
                0.0
            ],
            0.0
        ],
        "path_sensor_jumper_length_max": [
            19.998360154844473,
            19.99415936301654,
            19.998360154844473
        ],
        "path_sensor_jumper_length_avg": [
            9.477176839167015,
            9.291861088691824,
            9.641046027868592,
            [
                0.7850089528048873,
                1.7161465401159852,
                4.620258589261514,
                14.594699806023147,
                17.813768401701136,
                18.86275773867024
            ],
            9.62267415985891
        ],
        "path_router_node_branches_max": [
            2.0,
            2.0,
            2.0
        ],
        "path_router_node_branches_avg": [
            2.0,
            2.0,
            2.0,
            [
                2.0,
                2.0,
                2.0,
                2.0,
                2.0,
                2.0
            ],
            2.0
        ],
        "graph_max_wire_length": [
            741.5200756163666,
            692.9591552032713,
            809.431080582509,
            [
                325.3075191862683,
                359.97435737866624,
                527.7303200231618,
                877.2641555748796,
                931.8202201069106,
                998.4620012600939
            ],
            700.8793748281414
        ],
        "graph_avg_wire_length": [
            437.3461555853102,
            427.6829878391058,
            468.0966053639137,
            [
                194.17503253148575,
                206.70392413203209,
                299.4312543272464,
                507.3469246752062,
                577.2035823054007,
                608.0240912743643
            ],
            416.57321063654615
        ],
        "graph_max_node_count": [
            5.5,
            5.0,
            6.0,
            [
                3.0,
                3.0,
                4.0,
                6.0,
                7.0,
                7.0
            ],
            5.12
        ],
        "graph_avg_node_count": [
            3.3,
            3.1,
            3.45,
            [
                2.0,
                2.0,
                2.5,
                3.75,
                4.05,
                4.05
            ],
            3.150833333333334
        ],
        "graph_max_jumper_count": [
            0.0,
            0.0,
            0.0,
            [
                0.0,
                0.0,
                0.0,
                0.0,
                0.0,
                0.0
            ],
            0.0
        ],
        "graph_avg_jumper_count": [
            0.0,
            0.0,
            0.0,
            [
                0.0,
                0.0,
                0.0,
                0.0,
                0.0,
                0.0
            ],
            0.0
        ]
    },
    "least_jumper_path": {
        "percent_useful_node_count": [
            0.18518518518518517,
            0.16666666666666666,
            0.18518518518518517,
            [
                0.05555555555555555,
                0.05555555555555555,
                0.07407407407407407,
                0.18518518518518517,
                0.2037037037037037,
                0.2037037037037037
            ],
            0.15037037037037035
        ],
        "percent_useful_wire_length": 21.452537797702906,
        "percent_reachable_sensors": 0.08022,
        "percent_useful_jumper_count": [
            -1.0,
            -1.0,
            -1.0,
            [
                -1.0,
                -1.0,
                -1.0,
                -1.0,
                -1.0,
                -1.0
            ],
            -1.0
        ],
        "percent_useful_jumper_length": [
            -1.0,
            -1.0,
            -1.0,
            [
                -1.0,
                -1.0,
                -1.0,
                -1.0,
                -1.0,
                -1.0
            ],
            -1.0
        ],
        "percent_unreachable_bc_short_jumper": 0.74395,
        "percent_multiroute_reached_nodes": [
            0.7777777777777778,
            0.75,
            0.788888888888889,
            [
                0.6666666666666666,
                0.6666666666666666,
                0.7,
                0.8,
                0.9100000000000009,
                1.0
            ],
            0.7743080808080808
        ],
        "path_length_max": [
            1071.1055327213257,
            1052.7756285009516,
            1071.1055327213257
        ],
        "path_length_avg": [
            422.63728478415555,
            415.8567870573297,
            428.09379087618373,
            [
                133.3416016279965,
                165.36942803157433,
                256.6149536417428,
                576.3919113508063,
                709.1402331733476,
                772.9927351767234
            ],
            428.812133904685
        ],
        "path_node_count_max": [
            7.0,
            7.0,
            7.0
        ],
        "path_node_count_avg": [
            2.0,
            2.0,
            2.0,
            [
                1.0,
                1.0,
                1.0,
                3.0,
                4.0,
                4.0
            ],
            2.419346796310147
        ],
        "path_jumper_count_max": [
            0.0,
            0.0,
            0.0
        ],
        "path_jumper_count_avg": [
            0.0,
            0.0,
            0.0,
            [
                0.0,
                0.0,
                0.0,
                0.0,
                0.0,
                0.0
            ],
            0.0
        ],
        "path_sensor_jumper_length_max": [
            19.998360154844473,
            19.99415936301654,
            19.998360154844473
        ],
        "path_sensor_jumper_length_avg": [
            9.477176839167015,
            9.27166968932861,
            9.636465322847446,
            [
                0.7850089528048873,
                1.7161465401159852,
                4.620258589261514,
                14.594699806023147,
                17.813768401701136,
                18.86275773867024
            ],
            9.62267415985891
        ],
        "path_router_node_branches_max": [
            2.0,
            2.0,
            2.0
        ],
        "path_router_node_branches_avg": [
            2.0,
            2.0,
            2.0,
            [
                2.0,
                2.0,
                2.0,
                2.0,
                2.0,
                2.0
            ],
            2.0
        ],
        "graph_max_wire_length": [
            741.5200756163666,
            689.2461394980285,
            804.8811519182152,
            [
                325.3075191862683,
                359.97435737866624,
                527.7303200231618,
                877.2641555748796,
                931.8202201069106,
                998.4620012600939
            ],
            700.8793748281414
        ],
        "graph_avg_wire_length": [
            437.3461555853102,
            427.88262158355286,
            466.52210290533213,
            [
                194.17503253148575,
                206.70392413203209,
                299.4312543272464,
                507.3469246752062,
                577.2035823054007,
                608.0240912743643
            ],
            416.57321063654615
        ],
        "graph_max_node_count": [
            5.5,
            5.0,
            6.0,
            [
                3.0,
                3.0,
                4.0,
                6.0,
                7.0,
                7.0
            ],
            5.12
        ],
        "graph_avg_node_count": [
            3.3,
            3.1,
            3.45,
            [
                2.0,
                2.0,
                2.5,
                3.75,
                4.05,
                4.05
            ],
            3.150833333333334
        ],
        "graph_max_jumper_count": [
            0.0,
            0.0,
            0.0,
            [
                0.0,
                0.0,
                0.0,
                0.0,
                0.0,
                0.0
            ],
            0.0
        ],
        "graph_avg_jumper_count": [
            0.0,
            0.0,
            0.0,
            [
                0.0,
                0.0,
                0.0,
                0.0,
                0.0,
                0.0
            ],
            0.0
        ]
    }
}