{
    "total_wire_length": 243498.68135958412,
    "total_jumper_length": 11268.430834554387,
    "total_jumper_count": 1107,
    "center_node_count": 4872,
    "edge_node_count": 916,
    "total_node_count": 5788,
    "reachable_node_count": [
        5788.0,
        5788.0,
        5788.0,
        [
            5788.0,
            5788.0,
            5788.0,
            5788.0,
            5788.0,
            5788.0
        ],
        5788.0
    ],
    "unreachable_node_count": [
        0.0,
        0.0,
        0.0,
        [
            0.0,
            0.0,
            0.0,
            0.0,
            0.0,
            0.0
        ],
        0.0
    ],
    "reachable_wire_length": [
        243498.6813595841,
        243498.6813595841,
        243498.6813595841,
        [
            243498.6813595841,
            243498.6813595841,
            243498.6813595841,
            243498.6813595841,
            243498.6813595841,
            243498.6813595841
        ],
        243498.68135958406
    ],
    "unreachable_wire_length": [
        0.0,
        0.0,
        0.0,
        [
            0.0,
            0.0,
            0.0,
            0.0,
            0.0,
            0.0
        ],
        0.0
    ],
    "reachable_jumper_length": [
        11268.43083455436,
        11268.43083455436,
        11268.43083455436,
        [
            11268.43083455436,
            11268.43083455436,
            11268.43083455436,
            11268.43083455436,
            11268.43083455436,
            11268.43083455436
        ],
        11268.430834554358
    ],
    "unreachable_jumper_length": [
        0.0,
        0.0,
        0.0,
        [
            0.0,
            0.0,
            0.0,
            0.0,
            0.0,
            0.0
        ],
        0.0
    ],
    "reachable_jumper_count": [
        1107.0,
        1107.0,
        1107.0,
        [
            1107.0,
            1107.0,
            1107.0,
            1107.0,
            1107.0,
            1107.0
        ],
        1107.0
    ],
    "unreachable_jumper_count": [
        0.0,
        0.0,
        0.0,
        [
            0.0,
            0.0,
            0.0,
            0.0,
            0.0,
            0.0
        ],
        0.0
    ],
    "shortest_path": {
        "percent_useful_node_count": [
            0.6072045611610228,
            0.6046108327574292,
            0.6112646855563234,
            [
                0.5832325501036627,
                0.5880787836903939,
                0.6003369039391846,
                0.6185210780926054,
                0.6401693158258466,
                0.650449205252246
            ],
            0.6114651002073255
        ],
        "percent_useful_wire_length": 27.557592166586744,
        "percent_reachable_sensors": 1.0,
        "percent_useful_jumper_count": [
            0.17389340560072267,
            0.16982836495031617,
            0.17660343270099366,
            [
                0.14173441734417344,
                0.14724480578139115,
                0.15808491418247517,
                0.1842818428184282,
                0.1915989159891599,
                0.19516711833785005
            ],
            0.17138211382113816
        ],
        "percent_useful_jumper_length": [
            0.004516711833785004,
            0.004516711833785004,
            0.004516711833785004,
            [
                0.0027100271002710027,
                0.0035230352303523035,
                0.0036133694670280035,
                0.004516711833785004,
                0.005420054200542005,
                0.005420054200542005
            ],
            0.004209575429087625
        ],
        "percent_unreachable_bc_short_jumper": 0.0,
        "percent_multiroute_reached_nodes": [
            0.35753139542178547,
            0.3503398944593234,
            0.3683209445338046,
            [
                0.2696480138063077,
                0.28000255299928317,
                0.3238999465019575,
                0.37602543537464284,
                0.39247737890184514,
                0.4007280137360482
            ],
            0.34786082687532066
        ],
        "path_length_max": [
            1468.308307053427,
            1447.6526823217825,
            1468.308307053427
        ],
        "path_length_avg": [
            665.4018090872835,
            663.0990780956829,
            667.5697267181905,
            [
                205.5027373689436,
                286.29381200747275,
                455.32702760036995,
                848.8955507736196,
                1006.1418668098232,
                1095.1096128652357
            ],
            655.3807561045683
        ],
        "path_node_count_max": [
            84.0,
            83.0,
            84.0
        ],
        "path_node_count_avg": [
            35.0,
            35.0,
            35.0,
            [
                11.0,
                15.0,
                24.0,
                45.0,
                54.0,
                59.0
            ],
            34.90473
        ],
        "path_jumper_count_max": [
            68.0,
            66.0,
            68.0
        ],
        "path_jumper_count_avg": [
            1.0,
            1.0,
            1.0,
            [
                0.0,
                0.0,
                0.0,
                2.0,
                8.0,
                15.0
            ],
            2.84633
        ],
        "path_sensor_jumper_length_max": [
            11.609146752683458,
            10.163266376138793,
            11.609146752683458
        ],
        "path_sensor_jumper_length_avg": [
            2.2247414378909203,
            2.2076534631368996,
            2.241620939976732,
            [
                0.18925151670237134,
                0.3814835563495658,
                1.0089421072200881,
                3.889555954107682,
                5.700053232224989,
                6.9497826102183495
            ],
            2.6855203660978137
        ],
        "path_router_node_branches_max": [
            4.0,
            4.0,
            4.0
        ],
        "path_router_node_branches_avg": [
            2.0,
            2.0,
            2.0,
            [
                2.0,
                2.0,
                2.0,
                2.0,
                2.0,
                3.0
            ],
            2.094074074074074
        ],
        "graph_max_wire_length": [
            1241.5812644772113,
            1205.4577970141465,
            1264.483640609422,
            [
                1016.2693222789953,
                1035.1088723686414,
                1123.349700582473,
                1318.4025967463238,
                1370.310419988204,
                1389.0592869604222
            ],
            1222.5734136020008
        ],
        "graph_avg_wire_length": [
            638.3684768875087,
            621.930297578434,
            656.7678271540619,
            [
                574.3650587277112,
                582.2954448762321,
                595.9281164268692,
                707.2029205100499,
                762.6421732841507,
                786.7314563757303
            ],
            656.1639468549054
        ],
        "graph_max_node_count": [
            69.0,
            66.0,
            71.0,
            [
                55.0,
                57.9,
                62.0,
                74.0,
                80.0,
                83.05
            ],
            68.65
        ],
        "graph_avg_node_count": [
            35.16403201112436,
            33.72968722697886,
            35.74510859809729,
            [
                30.808121631310406,
                31.250784460247775,
                31.87461151215634,
                38.49386739499578,
                41.14112848160815,
                42.247364995692976
            ],
            35.548829419512195
        ],
        "graph_max_jumper_count": [
            40.0,
            32.0,
            43.0,
            [
                21.9,
                23.9,
                27.75,
                53.0,
                60.0,
                66.05
            ],
            40.68
        ],
        "graph_avg_jumper_count": [
            2.2553561753277878,
            2.0473133993229107,
            3.033764501925929,
            [
                1.390546263438161,
                1.5571405366471711,
                1.7764107023382278,
                3.701297788605697,
                4.773504216119373,
                5.367775829267654
            ],
            2.818951972597934
        ]
    },
    "least_jumper_path": {
        "percent_useful_node_count": [
            0.5622840359364202,
            0.5607290946786454,
            0.5661778680027644,
            [
                0.5383206634416033,
                0.5458016586040083,
                0.5538614374568072,
                0.5714409122322046,
                0.5881478921907394,
                0.5922857636489288
            ],
            0.5640272978576365
        ],
        "percent_useful_wire_length": 26.76225816767657,
        "percent_reachable_sensors": 1.0,
        "percent_useful_jumper_count": [
            0.1565215414937641,
            0.14986791918063105,
            0.16200339638501354,
            [
                0.11516060304098982,
                0.1204953720820461,
                0.1389195013404532,
                0.17025692009321025,
                0.1776934849330131,
                0.18413540961853034
            ],
            0.15288005152625297
        ],
        "percent_useful_jumper_length": [
            0.00502402651337373,
            0.004689160200942963,
            0.005623736750694868,
            [
                0.0026360362013688205,
                0.0034008377768873516,
                0.0041637035442760595,
                0.006122828137890895,
                0.006838888962579207,
                0.007230822510569873
            ],
            0.005103967753753031
        ],
        "percent_unreachable_bc_short_jumper": 0.0,
        "percent_multiroute_reached_nodes": [
            0.36056853571468117,
            0.3508849465855495,
            0.36816147236734986,
            [
                0.2948350215737833,
                0.30494833614670336,
                0.3317133079104332,
                0.38041851109186287,
                0.3965648862905165,
                0.4057678225033123
            ],
            0.3544030752536632
        ],
        "path_length_max": [
            1681.8506217996605,
            1656.702792875909,
            1681.8506217996605
        ],
        "path_length_avg": [
            719.488412969005,
            716.5727562473949,
            721.7817883744599,
            [
                213.2606124592376,
                302.45798821212827,
                486.26201351703503,
                945.4343820317093,
                1133.230684852319,
                1237.2281203948503
            ],
            720.1681500497614
        ],
        "path_node_count_max": [
            85.0,
            84.0,
            85.0
        ],
        "path_node_count_avg": [
            37.0,
            37.0,
            37.0,
            [
                11.0,
                15.0,
                25.0,
                48.0,
                58.0,
                63.0
            ],
            36.69263
        ],
        "path_jumper_count_max": [
            3.0,
            3.0,
            3.0
        ],
        "path_jumper_count_avg": [
            1.0,
            1.0,
            1.0,
            [
                0.0,
                0.0,
                0.0,
                1.0,
                1.0,
                2.0
            ],
            0.72067
        ],
        "path_sensor_jumper_length_max": [
            11.609146752683458,
            10.163266376138793,
            11.609146752683458
        ],
        "path_sensor_jumper_length_avg": [
            2.2247414378909203,
            2.2075344860915775,
            2.2412495244097865,
            [
                0.18925151670237134,
                0.3814835563495658,
                1.0089421072200881,
                3.889555954107682,
                5.700053232224989,
                6.9497826102183495
            ],
            2.6855203660978137
        ],
        "path_router_node_branches_max": [
            4.0,
            4.0,
            4.0
        ],
        "path_router_node_branches_avg": [
            2.0,
            2.0,
            2.0,
            [
                2.0,
                2.0,
                2.0,
                2.0,
                3.0,
                3.0
            ],
            2.1288445552784703
        ],
        "graph_max_wire_length": [
            1440.5325061541098,
            1410.457592913946,
            1465.2166869406647,
            [
                1226.9979316137562,
                1289.6436076080108,
                1347.9563560900733,
                1539.8804371593128,
                1579.7174664277122,
                1633.667543412844
            ],
            1438.837043265124
        ],
        "graph_avg_wire_length": [
            648.6012428309823,
            637.3934030478451,
            666.0768969562838,
            [
                578.2748318964047,
                586.7741703032287,
                602.5051681177954,
                723.3930258031061,
                771.935352223826,
                795.2959573884332
            ],
            666.2244252615737
        ],
        "graph_max_node_count": [
            74.0,
            73.0,
            75.0,
            [
                64.0,
                65.9,
                70.0,
                79.0,
                81.10000000000001,
                84.05
            ],
            74.09
        ],
        "graph_avg_node_count": [
            33.75006391876257,
            33.12624121479156,
            34.7430737062206,
            [
                29.993744450849032,
                30.344823106910567,
                31.03925382074874,
                37.16218445765487,
                39.983774011309706,
                40.67581089859649
            ],
            34.492565131141475
        ],
        "graph_max_jumper_count": [
            2.0,
            1.0,
            2.0,
            [
                1.0,
                1.0,
                1.0,
                2.0,
                2.0,
                2.0
            ],
            1.54
        ],
        "graph_avg_jumper_count": [
            0.4435468531034188,
            0.4363033226402713,
            0.4648392780416346,
            [
                0.38082974167012623,
                0.390553421333188,
                0.41277403475301655,
                0.5138579256666506,
                1.0848453802164144,
                1.1271791783710448
            ],
            0.5581261488450108
        ]
    }
}